QIWIAPI/Errors.py
QIWIAPI/Session.py
QIWIAPI/__init__.py
QIWIAPI/__version__.py
QIWIAPI/qiwiapi.py
QIWIAPI-5.0.dist-info/DESCRIPTION.rst
QIWIAPI-5.0.dist-info/METADATA
QIWIAPI-5.0.dist-info/RECORD
QIWIAPI-5.0.dist-info/WHEEL
QIWIAPI-5.0.dist-info/metadata.json
QIWIAPI-5.0.dist-info/top_level.txt
