Metadata-Version: 2.0
Name: QIWIAPI
Version: 5.0
Summary: Anonymous transactions in QIWI wallets
Home-page: https://github.com/stoner1776/QIWIAPI/
Author: StoNeR 1776
Author-email: stoner1776@gmail.com
License: MIT
Platform: UNKNOWN
Classifier: Development Status :: 5 - Production/Stable
Classifier: Intended Audience :: Developers
Classifier: License :: OSI Approved :: MIT License
Classifier: Natural Language :: English
Classifier: Programming Language :: Python :: 3
Classifier: Programming Language :: Python :: 3.4
Classifier: Programming Language :: Python :: 3.5
Classifier: Programming Language :: Python :: 3.6
Requires-Dist: certifi (==2018.4.16)
Requires-Dist: chardet (<4,==3.0.4)
Requires-Dist: idna (<3,==2.7)
Requires-Dist: requests (<3,==2.19.1)
Requires-Dist: urllib3 (<2,==1.23)
Requires-Dist: uuid (<2,==1.30)
